{"times": [{"trip_id": "6881768", "route_short_name": "603", "route_color": "#FF0000", "arrival_time": "05:16:01", "departure_time": "05:16:01", "stop_sequence": 3, "headsign": "Praça Rui Barbosa"}, {"trip_id": "6881814", "route_short_name": "603", "route_color": "#FF0000", "arrival_time": "05:25:01", "departure_time": "05:25:01", "stop_sequence": 3, "headsign": "Praça Rui Barbosa"}, {"trip_id": "6881526", "route_short_name": "502", "route_color": "#FF0000", "arrival_time": "05:27:36", "departure_time": "05:27:36", "stop_sequence": 9, "headsign": "Terminal Pinheirinho"}, {"trip_id": "6881560", "route_short_name": "502", "route_color": "#FF0000", "arrival_time": "05:33:52", "departure_time": "05:33:52", "stop_sequence": 9, "headsign": "Terminal Pinheirinho"}, {"trip_id": "6881837", "route_short_name": "603", "route_color": "#FF0000", "arrival_time": "05:34:01", "departure_time": "05:34:01", "stop_sequence": 3, "headsign": "Praça Rui Barbosa"}, {"trip_id": "6881897", "route_short_name": "603", "route_color": "#FF0000", "arrival_time": "05:38:01", "departure_time": "05:38:01", "stop_sequence": 3, "headsign": "Praça Rui Barbosa"}, {"trip_id": "6881521", "route_short_name": "502", "route_color": "#FF0000", "arrival_time": "05:39:52", "departure_time": "05:39:52", "stop_sequence": 18, "headsign": "Terminal Sitio Cercado"}, {"trip_id": "6881913", "route_short_name": "603", "route_color": "#FF0000", "arrival_time": "05:43:01", "departure_time": "05:43:01", "stop_sequence": 3, "headsign": "Praça Rui Barbosa"}, {"trip_id": "6881939", "route_short_name": "603", "route_color": "#FF0000", "arrival_time": "05:47:01", "departure_time": "05:47:01", "stop_sequence": 3, "headsign": "Praça Rui Barbosa"}, {"trip_id": "6881555", "route_short_name": "502", "route_color": "#FF0000", "arrival_time": "05:47:08", "departure_time": "05:47:08", "stop_sequence": 18, "headsign": "Terminal Sitio Cercado"}, {"trip_id": "6881949", "route_short_name": "603", "route_color": "#FF0000", "arrival_time": "05:52:01", "departure_time": "05:52:01", "stop_sequence": 3, "headsign": "Praça Rui Barbosa"}, {"trip_id": "6881577", "route_short_name": "502", "route_color": "#FF0000", "arrival_time": "05:53:39", "departure_time": "05:53:39", "stop_sequence": 9, "headsign": "Terminal Pinheirinho"}, {"trip_id": "6881978", "route_short_name": "603", "route_color": "#FF0000", "arrival_time": "05:56:01", "departure_time": "05:56:01", "stop_sequence": 3, "headsign": "Praça Rui Barbosa"}, {"trip_id": "6881572", "route_short_name": "502", "route_color": "#FF0000", "arrival_time": "06:00:39", "departure_time": "06:00:39", "stop_sequence": 18, "headsign": "Terminal Sitio Cercado"}, {"trip_id": "6881792", "route_short_name": "603", "route_color": "#FF0000", "arrival_time": "06:01:01", "departure_time": "06:01:01", "stop_sequence": 3, "headsign": "Praça Rui Barbosa"}, {"trip_id": "6881988", "route_short_name": "603", "route_color": "#FF0000", "arrival_time": "06:05:01", "departure_time": "06:05:01", "stop_sequence": 3, "headsign": "Praça Rui Barbosa"}, {"trip_id": "6881632", "route_short_name": "502", "route_color": "#FF0000", "arrival_time": "06:07:39", "departure_time": "06:07:39", "stop_sequence": 9, "headsign": "Terminal Pinheirinho"}, {"trip_id": "6881867", "route_short_name": "603", "route_color": "#FF0000", "arrival_time": "06:10:01", "departure_time": "06:10:01", "stop_sequence": 3, "headsign": "Praça Rui Barbosa"}, {"trip_id": "6881659", "route_short_name": "502", "route_color": "#FF0000", "arrival_time": "06:13:39", "departure_time": "06:13:39", "stop_sequence": 18, "headsign": "Terminal Sitio Cercado"}, {"trip_id": "6882000", "route_short_name": "603", "route_color": "#FF0000", "arrival_time": "06:14:01", "departure_time": "06:14:01", "stop_sequence": 3, "headsign": "Praça Rui Barbosa"}, {"trip_id": "6881935", "route_short_name": "603", "route_color": "#FF0000", "arrival_time": "06:19:01", "departure_time": "06:19:01", "stop_sequence": 3, "headsign": "Praça Rui Barbosa"}, {"trip_id": "6881598", "route_short_name": "502", "route_color": "#FF0000", "arrival_time": "06:19:39", "departure_time": "06:19:39", "stop_sequence": 18, "headsign": "Terminal Sitio Cercado"}, {"trip_id": "6882021", "route_short_name": "603", "route_color": "#FF0000", "arrival_time": "06:23:01", "departure_time": "06:23:01", "stop_sequence": 3, "headsign": "Praça Rui Barbosa"}, {"trip_id": "6881627", "route_short_name": "502", "route_color": "#FF0000", "arrival_time": "06:25:39", "departure_time": "06:25:39", "stop_sequence": 18, "headsign": "Terminal Sitio Cercado"}, {"trip_id": "6881770", "route_short_name": "603", "route_color": "#FF0000", "arrival_time": "06:28:01", "departure_time": "06:28:01", "stop_sequence": 3, "headsign": "Praça Rui Barbosa"}, {"trip_id": "6881669", "route_short_name": "502", "route_color": "#FF0000", "arrival_time": "06:31:39", "departure_time": "06:31:39", "stop_sequence": 9, "headsign": "Terminal Pinheirinho"}, {"trip_id": "6882048", "route_short_name": "603", "route_color": "#FF0000", "arrival_time": "06:32:01", "departure_time": "06:32:01", "stop_sequence": 3, "headsign": "Praça Rui Barbosa"}, {"trip_id": "6881528", "route_short_name": "502", "route_color": "#FF0000", "arrival_time": "06:36:39", "departure_time": "06:36:39", "stop_sequence": 9, "headsign": "Terminal Pinheirinho"}, {"trip_id": "6881816", "route_short_name": "603", "route_color": "#FF0000", "arrival_time": "06:37:01", "departure_time": "06:37:01", "stop_sequence": 3, "headsign": "Praça Rui Barbosa"}, {"trip_id": "6882051", "route_short_name": "603", "route_color": "#FF0000", "arrival_time": "06:41:01", "departure_time": "06:41:01", "stop_sequence": 3, "headsign": "Praça Rui Barbosa"}, {"trip_id": "6881562", "route_short_name": "502", "route_color": "#FF0000", "arrival_time": "06:42:39", "departure_time": "06:42:39", "stop_sequence": 9, "headsign": "Terminal Pinheirinho"}, {"trip_id": "6881839", "route_short_name": "603", "route_color": "#FF0000", "arrival_time": "06:46:01", "departure_time": "06:46:01", "stop_sequence": 3, "headsign": "Praça Rui Barbosa"}, {"trip_id": "6881696", "route_short_name": "502", "route_color": "#FF0000", "arrival_time": "06:48:39", "departure_time": "06:48:39", "stop_sequence": 9, "headsign": "Terminal Pinheirinho"}, {"trip_id": "6881899", "route_short_name": "603", "route_color": "#FF0000", "arrival_time": "06:50:01", "departure_time": "06:50:01", "stop_sequence": 3, "headsign": "Praça Rui Barbosa"}, {"trip_id": "6881523", "route_short_name": "502", "route_color": "#FF0000", "arrival_time": "06:54:39", "departure_time": "06:54:39", "stop_sequence": 18, "headsign": "Terminal Sitio Cercado"}, {"trip_id": "6881915", "route_short_name": "603", "route_color": "#FF0000", "arrival_time": "06:55:01", "departure_time": "06:55:01", "stop_sequence": 3, "headsign": "Praça Rui Barbosa"}, {"trip_id": "6881941", "route_short_name": "603", "route_color": "#FF0000", "arrival_time": "06:59:01", "departure_time": "06:59:01", "stop_sequence": 3, "headsign": "Praça Rui Barbosa"}, {"trip_id": "6881715", "route_short_name": "502", "route_color": "#FF0000", "arrival_time": "07:00:39", "departure_time": "07:00:39", "stop_sequence": 9, "headsign": "Terminal Pinheirinho"}, {"trip_id": "6881951", "route_short_name": "603", "route_color": "#FF0000", "arrival_time": "07:04:01", "departure_time": "07:04:01", "stop_sequence": 3, "headsign": "Praça Rui Barbosa"}, {"trip_id": "6881557", "route_short_name": "502", "route_color": "#FF0000", "arrival_time": "07:05:39", "departure_time": "07:05:39", "stop_sequence": 18, "headsign": "Terminal Sitio Cercado"}, {"trip_id": "6881980", "route_short_name": "603", "route_color": "#FF0000", "arrival_time": "07:08:01", "departure_time": "07:08:01", "stop_sequence": 3, "headsign": "Praça Rui Barbosa"}, {"trip_id": "6881579", "route_short_name": "502", "route_color": "#FF0000", "arrival_time": "07:10:39", "departure_time": "07:10:39", "stop_sequence": 9, "headsign": "Terminal Pinheirinho"}, {"trip_id": "6881794", "route_short_name": "603", "route_color": "#FF0000", "arrival_time": "07:13:01", "departure_time": "07:13:01", "stop_sequence": 3, "headsign": "Praça Rui Barbosa"}, {"trip_id": "6881764", "route_short_name": "502", "route_color": "#FF0000", "arrival_time": "07:15:39", "departure_time": "07:15:39", "stop_sequence": 9, "headsign": "Terminal Pinheirinho"}, {"trip_id": "6881990", "route_short_name": "603", "route_color": "#FF0000", "arrival_time": "07:17:01", "departure_time": "07:17:01", "stop_sequence": 3, "headsign": "Praça Rui Barbosa"}, {"trip_id": "6881574", "route_short_name": "502", "route_color": "#FF0000", "arrival_time": "07:20:39", "departure_time": "07:20:39", "stop_sequence": 18, "headsign": "Terminal Sitio Cercado"}, {"trip_id": "6881869", "route_short_name": "603", "route_color": "#FF0000", "arrival_time": "07:22:01", "departure_time": "07:22:01", "stop_sequence": 3, "headsign": "Praça Rui Barbosa"}, {"trip_id": "6881634", "route_short_name": "502", "route_color": "#FF0000", "arrival_time": "07:25:39", "departure_time": "07:25:39", "stop_sequence": 9, "headsign": "Terminal Pinheirinho"}, {"trip_id": "6882002", "route_short_name": "603", "route_color": "#FF0000", "arrival_time": "07:26:07", "departure_time": "07:26:07", "stop_sequence": 3, "headsign": "Praça Rui Barbosa"}, {"trip_id": "6881661", "route_short_name": "502", "route_color": "#FF0000", "arrival_time": "07:30:39", "departure_time": "07:30:39", "stop_sequence": 18, "headsign": "Terminal Sitio Cercado"}], "day": "friday"}