{"times": [{"trip_id": "6880787", "route_short_name": "503", "route_color": "#FF0000", "arrival_time": "05:19:59", "departure_time": "05:19:59", "stop_sequence": 11, "headsign": "Praça Carlos Gomes"}, {"trip_id": "6880812", "route_short_name": "503", "route_color": "#FF0000", "arrival_time": "05:28:59", "departure_time": "05:28:59", "stop_sequence": 11, "headsign": "Praça Carlos Gomes"}, {"trip_id": "6880843", "route_short_name": "503", "route_color": "#FF0000", "arrival_time": "05:36:59", "departure_time": "05:36:59", "stop_sequence": 11, "headsign": "Praça Carlos Gomes"}, {"trip_id": "6880861", "route_short_name": "503", "route_color": "#FF0000", "arrival_time": "05:44:59", "departure_time": "05:44:59", "stop_sequence": 11, "headsign": "Praça Carlos Gomes"}, {"trip_id": "6880892", "route_short_name": "503", "route_color": "#FF0000", "arrival_time": "05:53:59", "departure_time": "05:53:59", "stop_sequence": 11, "headsign": "Praça Carlos Gomes"}, {"trip_id": "6880915", "route_short_name": "503", "route_color": "#FF0000", "arrival_time": "06:01:59", "departure_time": "06:01:59", "stop_sequence": 11, "headsign": "Praça Carlos Gomes"}, {"trip_id": "6880933", "route_short_name": "503", "route_color": "#FF0000", "arrival_time": "06:09:59", "departure_time": "06:09:59", "stop_sequence": 11, "headsign": "Praça Carlos Gomes"}, {"trip_id": "6880956", "route_short_name": "503", "route_color": "#FF0000", "arrival_time": "06:18:59", "departure_time": "06:18:59", "stop_sequence": 11, "headsign": "Praça Carlos Gomes"}, {"trip_id": "6880789", "route_short_name": "503", "route_color": "#FF0000", "arrival_time": "06:26:59", "departure_time": "06:26:59", "stop_sequence": 11, "headsign": "Praça Carlos Gomes"}, {"trip_id": "6880814", "route_short_name": "503", "route_color": "#FF0000", "arrival_time": "06:35:59", "departure_time": "06:35:59", "stop_sequence": 11, "headsign": "Praça Carlos Gomes"}, {"trip_id": "6880845", "route_short_name": "503", "route_color": "#FF0000", "arrival_time": "06:43:59", "departure_time": "06:43:59", "stop_sequence": 11, "headsign": "Praça Carlos Gomes"}, {"trip_id": "6880863", "route_short_name": "503", "route_color": "#FF0000", "arrival_time": "06:51:59", "departure_time": "06:51:59", "stop_sequence": 11, "headsign": "Praça Carlos Gomes"}, {"trip_id": "6880894", "route_short_name": "503", "route_color": "#FF0000", "arrival_time": "07:01:35", "departure_time": "07:01:35", "stop_sequence": 11, "headsign": "Praça Carlos Gomes"}, {"trip_id": "6880917", "route_short_name": "503", "route_color": "#FF0000", "arrival_time": "07:10:11", "departure_time": "07:10:11", "stop_sequence": 11, "headsign": "Praça Carlos Gomes"}, {"trip_id": "6880935", "route_short_name": "503", "route_color": "#FF0000", "arrival_time": "07:19:11", "departure_time": "07:19:11", "stop_sequence": 11, "headsign": "Praça Carlos Gomes"}, {"trip_id": "6880958", "route_short_name": "503", "route_color": "#FF0000", "arrival_time": "07:27:48", "departure_time": "07:27:48", "stop_sequence": 11, "headsign": "Praça Carlos Gomes"}, {"trip_id": "6880791", "route_short_name": "503", "route_color": "#FF0000", "arrival_time": "07:36:48", "departure_time": "07:36:48", "stop_sequence": 11, "headsign": "Praça Carlos Gomes"}, {"trip_id": "6880816", "route_short_name": "503", "route_color": "#FF0000", "arrival_time": "07:45:48", "departure_time": "07:45:48", "stop_sequence": 11, "headsign": "Praça Carlos Gomes"}, {"trip_id": "6880865", "route_short_name": "503", "route_color": "#FF0000", "arrival_time": "08:01:48", "departure_time": "08:01:48", "stop_sequence": 11, "headsign": "Praça Carlos Gomes"}, {"trip_id": "6880896", "route_short_name": "503", "route_color": "#FF0000", "arrival_time": "08:11:48", "departure_time": "08:11:48", "stop_sequence": 11, "headsign": "Praça Carlos Gomes"}, {"trip_id": "6880937", "route_short_name": "503", "route_color": "#FF0000", "arrival_time": "08:28:35", "departure_time": "08:28:35", "stop_sequence": 11, "headsign": "Praça Carlos Gomes"}, {"trip_id": "6880793", "route_short_name": "503", "route_color": "#FF0000", "arrival_time": "08:44:59", "departure_time": "08:44:59", "stop_sequence": 11, "headsign": "Praça Carlos Gomes"}, {"trip_id": "6880818", "route_short_name": "503", "route_color": "#FF0000", "arrival_time": "08:57:59", "departure_time": "08:57:59", "stop_sequence": 11, "headsign": "Praça Carlos Gomes"}, {"trip_id": "6880867", "route_short_name": "503", "route_color": "#FF0000", "arrival_time": "09:11:35", "departure_time": "09:11:35", "stop_sequence": 11, "headsign": "Praça Carlos Gomes"}, {"trip_id": "6880898", "route_short_name": "503", "route_color": "#FF0000", "arrival_time": "09:24:35", "departure_time": "09:24:35", "stop_sequence": 11, "headsign": "Praça Carlos Gomes"}, {"trip_id": "6880939", "route_short_name": "503", "route_color": "#FF0000", "arrival_time": "09:38:35", "departure_time": "09:38:35", "stop_sequence": 11, "headsign": "Praça Carlos Gomes"}, {"trip_id": "6880795", "route_short_name": "503", "route_color": "#FF0000", "arrival_time": "09:51:59", "departure_time": "09:51:59", "stop_sequence": 11, "headsign": "Praça Carlos Gomes"}, {"trip_id": "6880820", "route_short_name": "503", "route_color": "#FF0000", "arrival_time": "10:05:59", "departure_time": "10:05:59", "stop_sequence": 11, "headsign": "Praça Carlos Gomes"}, {"trip_id": "6880869", "route_short_name": "503", "route_color": "#FF0000", "arrival_time": "10:19:59", "departure_time": "10:19:59", "stop_sequence": 11, "headsign": "Praça Carlos Gomes"}, {"trip_id": "6880900", "route_short_name": "503", "route_color": "#FF0000", "arrival_time": "10:32:59", "departure_time": "10:32:59", "stop_sequence": 11, "headsign": "Praça Carlos Gomes"}, {"trip_id": "6880941", "route_short_name": "503", "route_color": "#FF0000", "arrival_time": "10:46:59", "departure_time": "10:46:59", "stop_sequence": 11, "headsign": "Praça Carlos Gomes"}, {"trip_id": "6880797", "route_short_name": "503", "route_color": "#FF0000", "arrival_time": "10:59:59", "departure_time": "10:59:59", "stop_sequence": 11, "headsign": "Praça Carlos Gomes"}, {"trip_id": "6880822", "route_short_name": "503", "route_color": "#FF0000", "arrival_time": "11:13:59", "departure_time": "11:13:59", "stop_sequence": 11, "headsign": "Praça Carlos Gomes"}, {"trip_id": "6880871", "route_short_name": "503", "route_color": "#FF0000", "arrival_time": "11:27:59", "departure_time": "11:27:59", "stop_sequence": 11, "headsign": "Praça Carlos Gomes"}, {"trip_id": "6880902", "route_short_name": "503", "route_color": "#FF0000", "arrival_time": "11:42:59", "departure_time": "11:42:59", "stop_sequence": 11, "headsign": "Praça Carlos Gomes"}, {"trip_id": "6880943", "route_short_name": "503", "route_color": "#FF0000", "arrival_time": "11:56:59", "departure_time": "11:56:59", "stop_sequence": 11, "headsign": "Praça Carlos Gomes"}, {"trip_id": "6880799", "route_short_name": "503", "route_color": "#FF0000", "arrival_time": "12:10:59", "departure_time": "12:10:59", "stop_sequence": 11, "headsign": "Praça Carlos Gomes"}, {"trip_id": "6880824", "route_short_name": "503", "route_color": "#FF0000", "arrival_time": "12:23:59", "departure_time": "12:23:59", "stop_sequence": 11, "headsign": "Praça Carlos Gomes"}, {"trip_id": "6880873", "route_short_name": "503", "route_color": "#FF0000", "arrival_time": "12:36:59", "departure_time": "12:36:59", "stop_sequence": 11, "headsign": "Praça Carlos Gomes"}, {"trip_id": "6880904", "route_short_name": "503", "route_color": "#FF0000", "arrival_time": "12:50:59", "departure_time": "12:50:59", "stop_sequence": 11, "headsign": "Praça Carlos Gomes"}, {"trip_id": "6880945", "route_short_name": "503", "route_color": "#FF0000", "arrival_time": "13:04:59", "departure_time": "13:04:59", "stop_sequence": 11, "headsign": "Praça Carlos Gomes"}, {"trip_id": "6880801", "route_short_name": "503", "route_color": "#FF0000", "arrival_time": "13:18:59", "departure_time": "13:18:59", "stop_sequence": 11, "headsign": "Praça Carlos Gomes"}, {"trip_id": "6880826", "route_short_name": "503", "route_color": "#FF0000", "arrival_time": "13:32:59", "departure_time": "13:32:59", "stop_sequence": 11, "headsign": "Praça Carlos Gomes"}, {"trip_id": "6880875", "route_short_name": "503", "route_color": "#FF0000", "arrival_time": "13:45:59", "departure_time": "13:45:59", "stop_sequence": 11, "headsign": "Praça Carlos Gomes"}, {"trip_id": "6880906", "route_short_name": "503", "route_color": "#FF0000", "arrival_time": "13:59:59", "departure_time": "13:59:59", "stop_sequence": 11, "headsign": "Praça Carlos Gomes"}, {"trip_id": "6880947", "route_short_name": "503", "route_color": "#FF0000", "arrival_time": "14:12:59", "departure_time": "14:12:59", "stop_sequence": 11, "headsign": "Praça Carlos Gomes"}, {"trip_id": "6880803", "route_short_name": "503", "route_color": "#FF0000", "arrival_time": "14:26:59", "departure_time": "14:26:59", "stop_sequence": 11, "headsign": "Praça Carlos Gomes"}, {"trip_id": "6880828", "route_short_name": "503", "route_color": "#FF0000", "arrival_time": "14:40:22", "departure_time": "14:40:22", "stop_sequence": 11, "headsign": "Praça Carlos Gomes"}, {"trip_id": "6880877", "route_short_name": "503", "route_color": "#FF0000", "arrival_time": "14:53:59", "departure_time": "14:53:59", "stop_sequence": 11, "headsign": "Praça Carlos Gomes"}, {"trip_id": "6880908", "route_short_name": "503", "route_color": "#FF0000", "arrival_time": "15:07:59", "departure_time": "15:07:59", "stop_sequence": 11, "headsign": "Praça Carlos Gomes"}], "day": "friday"}