{"times": [{"trip_id": "6887005", "route_short_name": "387", "route_color": "#EFDC07", "arrival_time": "05:41:25", "departure_time": "05:41:25", "stop_sequence": 6, "headsign": "Praça Rui Barbosa"}, {"trip_id": "6887034", "route_short_name": "387", "route_color": "#EFDC07", "arrival_time": "06:20:25", "departure_time": "06:20:25", "stop_sequence": 6, "headsign": "Praça Rui Barbosa"}, {"trip_id": "6887007", "route_short_name": "387", "route_color": "#EFDC07", "arrival_time": "06:57:58", "departure_time": "06:57:58", "stop_sequence": 6, "headsign": "Praça Rui Barbosa"}, {"trip_id": "6887036", "route_short_name": "387", "route_color": "#EFDC07", "arrival_time": "07:37:23", "departure_time": "07:37:23", "stop_sequence": 6, "headsign": "Praça Rui Barbosa"}, {"trip_id": "6887009", "route_short_name": "387", "route_color": "#EFDC07", "arrival_time": "08:18:23", "departure_time": "08:18:23", "stop_sequence": 6, "headsign": "Praça Rui Barbosa"}, {"trip_id": "6887038", "route_short_name": "387", "route_color": "#EFDC07", "arrival_time": "08:57:15", "departure_time": "08:57:15", "stop_sequence": 6, "headsign": "Praça Rui Barbosa"}, {"trip_id": "6887011", "route_short_name": "387", "route_color": "#EFDC07", "arrival_time": "09:36:50", "departure_time": "09:36:50", "stop_sequence": 6, "headsign": "Praça Rui Barbosa"}, {"trip_id": "6887040", "route_short_name": "387", "route_color": "#EFDC07", "arrival_time": "10:15:33", "departure_time": "10:15:33", "stop_sequence": 6, "headsign": "Praça Rui Barbosa"}, {"trip_id": "6887013", "route_short_name": "387", "route_color": "#EFDC07", "arrival_time": "10:54:25", "departure_time": "10:54:25", "stop_sequence": 6, "headsign": "Praça Rui Barbosa"}, {"trip_id": "6887042", "route_short_name": "387", "route_color": "#EFDC07", "arrival_time": "11:33:25", "departure_time": "11:33:25", "stop_sequence": 6, "headsign": "Praça Rui Barbosa"}, {"trip_id": "6887015", "route_short_name": "387", "route_color": "#EFDC07", "arrival_time": "12:12:25", "departure_time": "12:12:25", "stop_sequence": 6, "headsign": "Praça Rui Barbosa"}, {"trip_id": "6887044", "route_short_name": "387", "route_color": "#EFDC07", "arrival_time": "12:51:25", "departure_time": "12:51:25", "stop_sequence": 6, "headsign": "Praça Rui Barbosa"}, {"trip_id": "6887017", "route_short_name": "387", "route_color": "#EFDC07", "arrival_time": "13:30:50", "departure_time": "13:30:50", "stop_sequence": 6, "headsign": "Praça Rui Barbosa"}, {"trip_id": "6887046", "route_short_name": "387", "route_color": "#EFDC07", "arrival_time": "14:09:50", "departure_time": "14:09:50", "stop_sequence": 6, "headsign": "Praça Rui Barbosa"}, {"trip_id": "6887019", "route_short_name": "387", "route_color": "#EFDC07", "arrival_time": "14:48:41", "departure_time": "14:48:41", "stop_sequence": 6, "headsign": "Praça Rui Barbosa"}, {"trip_id": "6887048", "route_short_name": "387", "route_color": "#EFDC07", "arrival_time": "15:27:33", "departure_time": "15:27:33", "stop_sequence": 6, "headsign": "Praça Rui Barbosa"}, {"trip_id": "6887021", "route_short_name": "387", "route_color": "#EFDC07", "arrival_time": "16:07:15", "departure_time": "16:07:15", "stop_sequence": 6, "headsign": "Praça Rui Barbosa"}, {"trip_id": "6887050", "route_short_name": "387", "route_color": "#EFDC07", "arrival_time": "16:52:06", "departure_time": "16:52:06", "stop_sequence": 6, "headsign": "Praça Rui Barbosa"}, {"trip_id": "6887023", "route_short_name": "387", "route_color": "#EFDC07", "arrival_time": "17:37:58", "departure_time": "17:37:58", "stop_sequence": 6, "headsign": "Praça Rui Barbosa"}, {"trip_id": "6887052", "route_short_name": "387", "route_color": "#EFDC07", "arrival_time": "18:23:50", "departure_time": "18:23:50", "stop_sequence": 6, "headsign": "Praça Rui Barbosa"}, {"trip_id": "6887025", "route_short_name": "387", "route_color": "#EFDC07", "arrival_time": "19:07:16", "departure_time": "19:07:16", "stop_sequence": 6, "headsign": "Praça Rui Barbosa"}, {"trip_id": "6887027", "route_short_name": "387", "route_color": "#EFDC07", "arrival_time": "20:19:51", "departure_time": "20:19:51", "stop_sequence": 6, "headsign": "Praça Rui Barbosa"}, {"trip_id": "6887029", "route_short_name": "387", "route_color": "#EFDC07", "arrival_time": "21:29:51", "departure_time": "21:29:51", "stop_sequence": 6, "headsign": "Praça Rui Barbosa"}, {"trip_id": "6887031", "route_short_name": "387", "route_color": "#EFDC07", "arrival_time": "22:39:51", "departure_time": "22:39:51", "stop_sequence": 6, "headsign": "Praça Rui Barbosa"}, {"trip_id": "6887033", "route_short_name": "387", "route_color": "#EFDC07", "arrival_time": "23:49:51", "departure_time": "23:49:51", "stop_sequence": 6, "headsign": "Praça Rui Barbosa"}], "day": "thursday"}