{"times": [{"trip_id": "6879435", "route_short_name": "615", "route_color": "#F98700", "arrival_time": "05:34:46", "departure_time": "05:34:46", "stop_sequence": 10, "headsign": "Portão"}, {"trip_id": "6879437", "route_short_name": "615", "route_color": "#F98700", "arrival_time": "06:04:55", "departure_time": "06:04:55", "stop_sequence": 10, "headsign": "Portão"}, {"trip_id": "6879451", "route_short_name": "615", "route_color": "#F98700", "arrival_time": "06:21:18", "departure_time": "06:21:18", "stop_sequence": 10, "headsign": "Portão"}, {"trip_id": "6879439", "route_short_name": "615", "route_color": "#F98700", "arrival_time": "06:37:41", "departure_time": "06:37:41", "stop_sequence": 10, "headsign": "Portão"}, {"trip_id": "6879453", "route_short_name": "615", "route_color": "#F98700", "arrival_time": "06:55:04", "departure_time": "06:55:04", "stop_sequence": 10, "headsign": "Portão"}, {"trip_id": "6879441", "route_short_name": "615", "route_color": "#F98700", "arrival_time": "07:12:27", "departure_time": "07:12:27", "stop_sequence": 10, "headsign": "Portão"}, {"trip_id": "6879455", "route_short_name": "615", "route_color": "#F98700", "arrival_time": "07:30:27", "departure_time": "07:30:27", "stop_sequence": 10, "headsign": "Portão"}, {"trip_id": "6879457", "route_short_name": "615", "route_color": "#F98700", "arrival_time": "08:06:27", "departure_time": "08:06:27", "stop_sequence": 10, "headsign": "Portão"}, {"trip_id": "6879459", "route_short_name": "615", "route_color": "#F98700", "arrival_time": "08:43:58", "departure_time": "08:43:58", "stop_sequence": 10, "headsign": "Portão"}, {"trip_id": "6879461", "route_short_name": "615", "route_color": "#F98700", "arrival_time": "09:23:58", "departure_time": "09:23:58", "stop_sequence": 10, "headsign": "Portão"}, {"trip_id": "6879463", "route_short_name": "615", "route_color": "#F98700", "arrival_time": "10:03:58", "departure_time": "10:03:58", "stop_sequence": 10, "headsign": "Portão"}, {"trip_id": "6879465", "route_short_name": "615", "route_color": "#F98700", "arrival_time": "10:43:58", "departure_time": "10:43:58", "stop_sequence": 10, "headsign": "Portão"}, {"trip_id": "6879467", "route_short_name": "615", "route_color": "#F98700", "arrival_time": "11:23:58", "departure_time": "11:23:58", "stop_sequence": 10, "headsign": "Portão"}, {"trip_id": "6879469", "route_short_name": "615", "route_color": "#F98700", "arrival_time": "12:03:58", "departure_time": "12:03:58", "stop_sequence": 10, "headsign": "Portão"}, {"trip_id": "6879471", "route_short_name": "615", "route_color": "#F98700", "arrival_time": "12:43:58", "departure_time": "12:43:58", "stop_sequence": 10, "headsign": "Portão"}, {"trip_id": "6879473", "route_short_name": "615", "route_color": "#F98700", "arrival_time": "13:23:58", "departure_time": "13:23:58", "stop_sequence": 10, "headsign": "Portão"}, {"trip_id": "6879475", "route_short_name": "615", "route_color": "#F98700", "arrival_time": "14:03:58", "departure_time": "14:03:58", "stop_sequence": 10, "headsign": "Portão"}, {"trip_id": "6879477", "route_short_name": "615", "route_color": "#F98700", "arrival_time": "14:43:58", "departure_time": "14:43:58", "stop_sequence": 10, "headsign": "Portão"}, {"trip_id": "6879479", "route_short_name": "615", "route_color": "#F98700", "arrival_time": "15:23:58", "departure_time": "15:23:58", "stop_sequence": 10, "headsign": "Portão"}, {"trip_id": "6879481", "route_short_name": "615", "route_color": "#F98700", "arrival_time": "16:04:04", "departure_time": "16:04:04", "stop_sequence": 10, "headsign": "Portão"}, {"trip_id": "6879483", "route_short_name": "615", "route_color": "#F98700", "arrival_time": "16:41:27", "departure_time": "16:41:27", "stop_sequence": 10, "headsign": "Portão"}, {"trip_id": "6879485", "route_short_name": "615", "route_color": "#F98700", "arrival_time": "17:22:58", "departure_time": "17:22:58", "stop_sequence": 10, "headsign": "Portão"}, {"trip_id": "6879444", "route_short_name": "615", "route_color": "#F98700", "arrival_time": "17:45:21", "departure_time": "17:45:21", "stop_sequence": 10, "headsign": "Portão"}, {"trip_id": "6879487", "route_short_name": "615", "route_color": "#F98700", "arrival_time": "18:07:44", "departure_time": "18:07:44", "stop_sequence": 10, "headsign": "Portão"}, {"trip_id": "6879446", "route_short_name": "615", "route_color": "#F98700", "arrival_time": "18:29:35", "departure_time": "18:29:35", "stop_sequence": 10, "headsign": "Portão"}, {"trip_id": "6879489", "route_short_name": "615", "route_color": "#F98700", "arrival_time": "18:51:27", "departure_time": "18:51:27", "stop_sequence": 10, "headsign": "Portão"}, {"trip_id": "6879448", "route_short_name": "615", "route_color": "#F98700", "arrival_time": "19:11:27", "departure_time": "19:11:27", "stop_sequence": 10, "headsign": "Portão"}, {"trip_id": "6879491", "route_short_name": "615", "route_color": "#F98700", "arrival_time": "19:31:27", "departure_time": "19:31:27", "stop_sequence": 10, "headsign": "Portão"}, {"trip_id": "6879493", "route_short_name": "615", "route_color": "#F98700", "arrival_time": "20:10:12", "departure_time": "20:10:12", "stop_sequence": 10, "headsign": "Portão"}, {"trip_id": "6879495", "route_short_name": "615", "route_color": "#F98700", "arrival_time": "20:48:50", "departure_time": "20:48:50", "stop_sequence": 10, "headsign": "Portão"}, {"trip_id": "6879497", "route_short_name": "615", "route_color": "#F98700", "arrival_time": "21:26:50", "departure_time": "21:26:50", "stop_sequence": 10, "headsign": "Portão"}, {"trip_id": "6879499", "route_short_name": "615", "route_color": "#F98700", "arrival_time": "22:04:50", "departure_time": "22:04:50", "stop_sequence": 10, "headsign": "Portão"}, {"trip_id": "6879501", "route_short_name": "615", "route_color": "#F98700", "arrival_time": "22:42:50", "departure_time": "22:42:50", "stop_sequence": 10, "headsign": "Portão"}, {"trip_id": "6879503", "route_short_name": "615", "route_color": "#F98700", "arrival_time": "23:20:50", "departure_time": "23:20:50", "stop_sequence": 10, "headsign": "Portão"}], "day": "thursday"}