{"weekday": [{"trip_id": "6873468", "route_short_name": "658", "route_color": "#F98700", "arrival_time": "05:36:43", "departure_time": "05:36:43", "stop_sequence": 44, "headsign": "Terminal Capão Raso"}, {"trip_id": "6878327", "route_short_name": "622", "route_color": "#F98700", "arrival_time": "05:41:32", "departure_time": "05:41:32", "stop_sequence": 23, "headsign": "Terminal Capão Raso"}, {"trip_id": "6873386", "route_short_name": "658", "route_color": "#F98700", "arrival_time": "05:47:41", "departure_time": "05:47:41", "stop_sequence": 44, "headsign": "Terminal Capão Raso"}, {"trip_id": "6873428", "route_short_name": "658", "route_color": "#F98700", "arrival_time": "05:58:41", "departure_time": "05:58:41", "stop_sequence": 44, "headsign": "Terminal Capão Raso"}, {"trip_id": "6873463", "route_short_name": "658", "route_color": "#F98700", "arrival_time": "06:09:41", "departure_time": "06:09:41", "stop_sequence": 44, "headsign": "Terminal Capão Raso"}, {"trip_id": "6873497", "route_short_name": "658", "route_color": "#F98700", "arrival_time": "06:20:41", "departure_time": "06:20:41", "stop_sequence": 44, "headsign": "Terminal Capão Raso"}, {"trip_id": "6878329", "route_short_name": "622", "route_color": "#F98700", "arrival_time": "06:26:32", "departure_time": "06:26:32", "stop_sequence": 23, "headsign": "Terminal Capão Raso"}, {"trip_id": "6873400", "route_short_name": "658", "route_color": "#F98700", "arrival_time": "06:31:41", "departure_time": "06:31:41", "stop_sequence": 44, "headsign": "Terminal Capão Raso"}, {"trip_id": "6873456", "route_short_name": "658", "route_color": "#F98700", "arrival_time": "06:43:39", "departure_time": "06:43:39", "stop_sequence": 44, "headsign": "Terminal Capão Raso"}, {"trip_id": "6873470", "route_short_name": "658", "route_color": "#F98700", "arrival_time": "06:55:37", "departure_time": "06:55:37", "stop_sequence": 44, "headsign": "Terminal Capão Raso"}, {"trip_id": "6873388", "route_short_name": "658", "route_color": "#F98700", "arrival_time": "07:07:35", "departure_time": "07:07:35", "stop_sequence": 44, "headsign": "Terminal Capão Raso"}, {"trip_id": "6878331", "route_short_name": "622", "route_color": "#F98700", "arrival_time": "07:12:28", "departure_time": "07:12:28", "stop_sequence": 23, "headsign": "Terminal Capão Raso"}, {"trip_id": "6873430", "route_short_name": "658", "route_color": "#F98700", "arrival_time": "07:19:33", "departure_time": "07:19:33", "stop_sequence": 44, "headsign": "Terminal Capão Raso"}, {"trip_id": "6873465", "route_short_name": "658", "route_color": "#F98700", "arrival_time": "07:32:29", "departure_time": "07:32:29", "stop_sequence": 44, "headsign": "Terminal Capão Raso"}, {"trip_id": "6873499", "route_short_name": "658", "route_color": "#F98700", "arrival_time": "07:45:25", "departure_time": "07:45:25", "stop_sequence": 44, "headsign": "Terminal Capão Raso"}, {"trip_id": "6878333", "route_short_name": "622", "route_color": "#F98700", "arrival_time": "08:00:28", "departure_time": "08:00:28", "stop_sequence": 23, "headsign": "Terminal Capão Raso"}, {"trip_id": "6873402", "route_short_name": "658", "route_color": "#F98700", "arrival_time": "08:01:17", "departure_time": "08:01:17", "stop_sequence": 44, "headsign": "Terminal Capão Raso"}, {"trip_id": "6873472", "route_short_name": "658", "route_color": "#F98700", "arrival_time": "08:22:23", "departure_time": "08:22:23", "stop_sequence": 44, "headsign": "Terminal Capão Raso"}, {"trip_id": "6873432", "route_short_name": "658", "route_color": "#F98700", "arrival_time": "08:42:31", "departure_time": "08:42:31", "stop_sequence": 44, "headsign": "Terminal Capão Raso"}, {"trip_id": "6878335", "route_short_name": "622", "route_color": "#F98700", "arrival_time": "08:49:24", "departure_time": "08:49:24", "stop_sequence": 23, "headsign": "Terminal Capão Raso"}, {"trip_id": "6873501", "route_short_name": "658", "route_color": "#F98700", "arrival_time": "09:02:43", "departure_time": "09:02:43", "stop_sequence": 44, "headsign": "Terminal Capão Raso"}, {"trip_id": "6873404", "route_short_name": "658", "route_color": "#F98700", "arrival_time": "09:22:41", "departure_time": "09:22:41", "stop_sequence": 44, "headsign": "Terminal Capão Raso"}, {"trip_id": "6878337", "route_short_name": "622", "route_color": "#F98700", "arrival_time": "09:36:28", "departure_time": "09:36:28", "stop_sequence": 23, "headsign": "Terminal Capão Raso"}, {"trip_id": "6873474", "route_short_name": "658", "route_color": "#F98700", "arrival_time": "09:42:39", "departure_time": "09:42:39", "stop_sequence": 44, "headsign": "Terminal Capão Raso"}, {"trip_id": "6873434", "route_short_name": "658", "route_color": "#F98700", "arrival_time": "10:02:39", "departure_time": "10:02:39", "stop_sequence": 44, "headsign": "Terminal Capão Raso"}, {"trip_id": "6873503", "route_short_name": "658", "route_color": "#F98700", "arrival_time": "10:22:39", "departure_time": "10:22:39", "stop_sequence": 44, "headsign": "Terminal Capão Raso"}, {"trip_id": "6878339", "route_short_name": "622", "route_color": "#F98700", "arrival_time": "10:24:24", "departure_time": "10:24:24", "stop_sequence": 23, "headsign": "Terminal Capão Raso"}, {"trip_id": "6873406", "route_short_name": "658", "route_color": "#F98700", "arrival_time": "10:42:39", "departure_time": "10:42:39", "stop_sequence": 44, "headsign": "Terminal Capão Raso"}, {"trip_id": "6873476", "route_short_name": "658", "route_color": "#F98700", "arrival_time": "11:02:39", "departure_time": "11:02:39", "stop_sequence": 44, "headsign": "Terminal Capão Raso"}, {"trip_id": "6878341", "route_short_name": "622", "route_color": "#F98700", "arrival_time": "11:11:28", "departure_time": "11:11:28", "stop_sequence": 23, "headsign": "Terminal Capão Raso"}, {"trip_id": "6873436", "route_short_name": "658", "route_color": "#F98700", "arrival_time": "11:22:39", "departure_time": "11:22:39", "stop_sequence": 44, "headsign": "Terminal Capão Raso"}, {"trip_id": "6873505", "route_short_name": "658", "route_color": "#F98700", "arrival_time": "11:39:45", "departure_time": "11:39:45", "stop_sequence": 44, "headsign": "Terminal Capão Raso"}, {"trip_id": "6873391", "route_short_name": "658", "route_color": "#F98700", "arrival_time": "11:56:39", "departure_time": "11:56:39", "stop_sequence": 44, "headsign": "Terminal Capão Raso"}, {"trip_id": "6878343", "route_short_name": "622", "route_color": "#F98700", "arrival_time": "11:58:28", "departure_time": "11:58:28", "stop_sequence": 23, "headsign": "Terminal Capão Raso"}, {"trip_id": "6873408", "route_short_name": "658", "route_color": "#F98700", "arrival_time": "12:13:33", "departure_time": "12:13:33", "stop_sequence": 44, "headsign": "Terminal Capão Raso"}, {"trip_id": "6873478", "route_short_name": "658", "route_color": "#F98700", "arrival_time": "12:30:31", "departure_time": "12:30:31", "stop_sequence": 44, "headsign": "Terminal Capão Raso"}, {"trip_id": "6873438", "route_short_name": "658", "route_color": "#F98700", "arrival_time": "12:46:31", "departure_time": "12:46:31", "stop_sequence": 44, "headsign": "Terminal Capão Raso"}, {"trip_id": "6878345", "route_short_name": "622", "route_color": "#F98700", "arrival_time": "12:47:24", "departure_time": "12:47:24", "stop_sequence": 23, "headsign": "Terminal Capão Raso"}, {"trip_id": "6873507", "route_short_name": "658", "route_color": "#F98700", "arrival_time": "13:03:29", "departure_time": "13:03:29", "stop_sequence": 44, "headsign": "Terminal Capão Raso"}, {"trip_id": "6873393", "route_short_name": "658", "route_color": "#F98700", "arrival_time": "13:19:31", "departure_time": "13:19:31", "stop_sequence": 44, "headsign": "Terminal Capão Raso"}, {"trip_id": "6873410", "route_short_name": "658", "route_color": "#F98700", "arrival_time": "13:35:33", "departure_time": "13:35:33", "stop_sequence": 44, "headsign": "Terminal Capão Raso"}, {"trip_id": "6878347", "route_short_name": "622", "route_color": "#F98700", "arrival_time": "13:36:24", "departure_time": "13:36:24", "stop_sequence": 23, "headsign": "Terminal Capão Raso"}, {"trip_id": "6873480", "route_short_name": "658", "route_color": "#F98700", "arrival_time": "13:52:33", "departure_time": "13:52:33", "stop_sequence": 44, "headsign": "Terminal Capão Raso"}, {"trip_id": "6873440", "route_short_name": "658", "route_color": "#F98700", "arrival_time": "14:09:39", "departure_time": "14:09:39", "stop_sequence": 44, "headsign": "Terminal Capão Raso"}, {"trip_id": "6878349", "route_short_name": "622", "route_color": "#F98700", "arrival_time": "14:24:28", "departure_time": "14:24:28", "stop_sequence": 23, "headsign": "Terminal Capão Raso"}, {"trip_id": "6873509", "route_short_name": "658", "route_color": "#F98700", "arrival_time": "14:30:37", "departure_time": "14:30:37", "stop_sequence": 44, "headsign": "Terminal Capão Raso"}, {"trip_id": "6873412", "route_short_name": "658", "route_color": "#F98700", "arrival_time": "14:52:35", "departure_time": "14:52:35", "stop_sequence": 44, "headsign": "Terminal Capão Raso"}, {"trip_id": "6878351", "route_short_name": "622", "route_color": "#F98700", "arrival_time": "15:12:28", "departure_time": "15:12:28", "stop_sequence": 23, "headsign": "Terminal Capão Raso"}, {"trip_id": "6873482", "route_short_name": "658", "route_color": "#F98700", "arrival_time": "15:14:33", "departure_time": "15:14:33", "stop_sequence": 44, "headsign": "Terminal Capão Raso"}, {"trip_id": "6873442", "route_short_name": "658", "route_color": "#F98700", "arrival_time": "15:36:31", "departure_time": "15:36:31", "stop_sequence": 44, "headsign": "Terminal Capão Raso"}], "saturday": [{"trip_id": "6873468", "route_short_name": "658", "route_color": "#F98700", "arrival_time": "05:36:43", "departure_time": "05:36:43", "stop_sequence": 44, "headsign": "Terminal Capão Raso"}, {"trip_id": "6878327", "route_short_name": "622", "route_color": "#F98700", "arrival_time": "05:41:32", "departure_time": "05:41:32", "stop_sequence": 23, "headsign": "Terminal Capão Raso"}, {"trip_id": "6873386", "route_short_name": "658", "route_color": "#F98700", "arrival_time": "05:47:41", "departure_time": "05:47:41", "stop_sequence": 44, "headsign": "Terminal Capão Raso"}, {"trip_id": "6873428", "route_short_name": "658", "route_color": "#F98700", "arrival_time": "05:58:41", "departure_time": "05:58:41", "stop_sequence": 44, "headsign": "Terminal Capão Raso"}, {"trip_id": "6873463", "route_short_name": "658", "route_color": "#F98700", "arrival_time": "06:09:41", "departure_time": "06:09:41", "stop_sequence": 44, "headsign": "Terminal Capão Raso"}, {"trip_id": "6873497", "route_short_name": "658", "route_color": "#F98700", "arrival_time": "06:20:41", "departure_time": "06:20:41", "stop_sequence": 44, "headsign": "Terminal Capão Raso"}, {"trip_id": "6878329", "route_short_name": "622", "route_color": "#F98700", "arrival_time": "06:26:32", "departure_time": "06:26:32", "stop_sequence": 23, "headsign": "Terminal Capão Raso"}, {"trip_id": "6873400", "route_short_name": "658", "route_color": "#F98700", "arrival_time": "06:31:41", "departure_time": "06:31:41", "stop_sequence": 44, "headsign": "Terminal Capão Raso"}, {"trip_id": "6873456", "route_short_name": "658", "route_color": "#F98700", "arrival_time": "06:43:39", "departure_time": "06:43:39", "stop_sequence": 44, "headsign": "Terminal Capão Raso"}, {"trip_id": "6873470", "route_short_name": "658", "route_color": "#F98700", "arrival_time": "06:55:37", "departure_time": "06:55:37", "stop_sequence": 44, "headsign": "Terminal Capão Raso"}, {"trip_id": "6873388", "route_short_name": "658", "route_color": "#F98700", "arrival_time": "07:07:35", "departure_time": "07:07:35", "stop_sequence": 44, "headsign": "Terminal Capão Raso"}, {"trip_id": "6878331", "route_short_name": "622", "route_color": "#F98700", "arrival_time": "07:12:28", "departure_time": "07:12:28", "stop_sequence": 23, "headsign": "Terminal Capão Raso"}, {"trip_id": "6873430", "route_short_name": "658", "route_color": "#F98700", "arrival_time": "07:19:33", "departure_time": "07:19:33", "stop_sequence": 44, "headsign": "Terminal Capão Raso"}, {"trip_id": "6873465", "route_short_name": "658", "route_color": "#F98700", "arrival_time": "07:32:29", "departure_time": "07:32:29", "stop_sequence": 44, "headsign": "Terminal Capão Raso"}, {"trip_id": "6873499", "route_short_name": "658", "route_color": "#F98700", "arrival_time": "07:45:25", "departure_time": "07:45:25", "stop_sequence": 44, "headsign": "Terminal Capão Raso"}, {"trip_id": "6878333", "route_short_name": "622", "route_color": "#F98700", "arrival_time": "08:00:28", "departure_time": "08:00:28", "stop_sequence": 23, "headsign": "Terminal Capão Raso"}, {"trip_id": "6873402", "route_short_name": "658", "route_color": "#F98700", "arrival_time": "08:01:17", "departure_time": "08:01:17", "stop_sequence": 44, "headsign": "Terminal Capão Raso"}, {"trip_id": "6873472", "route_short_name": "658", "route_color": "#F98700", "arrival_time": "08:22:23", "departure_time": "08:22:23", "stop_sequence": 44, "headsign": "Terminal Capão Raso"}, {"trip_id": "6873432", "route_short_name": "658", "route_color": "#F98700", "arrival_time": "08:42:31", "departure_time": "08:42:31", "stop_sequence": 44, "headsign": "Terminal Capão Raso"}, {"trip_id": "6878335", "route_short_name": "622", "route_color": "#F98700", "arrival_time": "08:49:24", "departure_time": "08:49:24", "stop_sequence": 23, "headsign": "Terminal Capão Raso"}, {"trip_id": "6873501", "route_short_name": "658", "route_color": "#F98700", "arrival_time": "09:02:43", "departure_time": "09:02:43", "stop_sequence": 44, "headsign": "Terminal Capão Raso"}, {"trip_id": "6873404", "route_short_name": "658", "route_color": "#F98700", "arrival_time": "09:22:41", "departure_time": "09:22:41", "stop_sequence": 44, "headsign": "Terminal Capão Raso"}, {"trip_id": "6878337", "route_short_name": "622", "route_color": "#F98700", "arrival_time": "09:36:28", "departure_time": "09:36:28", "stop_sequence": 23, "headsign": "Terminal Capão Raso"}, {"trip_id": "6873474", "route_short_name": "658", "route_color": "#F98700", "arrival_time": "09:42:39", "departure_time": "09:42:39", "stop_sequence": 44, "headsign": "Terminal Capão Raso"}, {"trip_id": "6873434", "route_short_name": "658", "route_color": "#F98700", "arrival_time": "10:02:39", "departure_time": "10:02:39", "stop_sequence": 44, "headsign": "Terminal Capão Raso"}, {"trip_id": "6873503", "route_short_name": "658", "route_color": "#F98700", "arrival_time": "10:22:39", "departure_time": "10:22:39", "stop_sequence": 44, "headsign": "Terminal Capão Raso"}, {"trip_id": "6878339", "route_short_name": "622", "route_color": "#F98700", "arrival_time": "10:24:24", "departure_time": "10:24:24", "stop_sequence": 23, "headsign": "Terminal Capão Raso"}, {"trip_id": "6873406", "route_short_name": "658", "route_color": "#F98700", "arrival_time": "10:42:39", "departure_time": "10:42:39", "stop_sequence": 44, "headsign": "Terminal Capão Raso"}, {"trip_id": "6873476", "route_short_name": "658", "route_color": "#F98700", "arrival_time": "11:02:39", "departure_time": "11:02:39", "stop_sequence": 44, "headsign": "Terminal Capão Raso"}, {"trip_id": "6878341", "route_short_name": "622", "route_color": "#F98700", "arrival_time": "11:11:28", "departure_time": "11:11:28", "stop_sequence": 23, "headsign": "Terminal Capão Raso"}, {"trip_id": "6873436", "route_short_name": "658", "route_color": "#F98700", "arrival_time": "11:22:39", "departure_time": "11:22:39", "stop_sequence": 44, "headsign": "Terminal Capão Raso"}, {"trip_id": "6873505", "route_short_name": "658", "route_color": "#F98700", "arrival_time": "11:39:45", "departure_time": "11:39:45", "stop_sequence": 44, "headsign": "Terminal Capão Raso"}, {"trip_id": "6873391", "route_short_name": "658", "route_color": "#F98700", "arrival_time": "11:56:39", "departure_time": "11:56:39", "stop_sequence": 44, "headsign": "Terminal Capão Raso"}, {"trip_id": "6878343", "route_short_name": "622", "route_color": "#F98700", "arrival_time": "11:58:28", "departure_time": "11:58:28", "stop_sequence": 23, "headsign": "Terminal Capão Raso"}, {"trip_id": "6873408", "route_short_name": "658", "route_color": "#F98700", "arrival_time": "12:13:33", "departure_time": "12:13:33", "stop_sequence": 44, "headsign": "Terminal Capão Raso"}, {"trip_id": "6873478", "route_short_name": "658", "route_color": "#F98700", "arrival_time": "12:30:31", "departure_time": "12:30:31", "stop_sequence": 44, "headsign": "Terminal Capão Raso"}, {"trip_id": "6873438", "route_short_name": "658", "route_color": "#F98700", "arrival_time": "12:46:31", "departure_time": "12:46:31", "stop_sequence": 44, "headsign": "Terminal Capão Raso"}, {"trip_id": "6878345", "route_short_name": "622", "route_color": "#F98700", "arrival_time": "12:47:24", "departure_time": "12:47:24", "stop_sequence": 23, "headsign": "Terminal Capão Raso"}, {"trip_id": "6873507", "route_short_name": "658", "route_color": "#F98700", "arrival_time": "13:03:29", "departure_time": "13:03:29", "stop_sequence": 44, "headsign": "Terminal Capão Raso"}, {"trip_id": "6873393", "route_short_name": "658", "route_color": "#F98700", "arrival_time": "13:19:31", "departure_time": "13:19:31", "stop_sequence": 44, "headsign": "Terminal Capão Raso"}, {"trip_id": "6873410", "route_short_name": "658", "route_color": "#F98700", "arrival_time": "13:35:33", "departure_time": "13:35:33", "stop_sequence": 44, "headsign": "Terminal Capão Raso"}, {"trip_id": "6878347", "route_short_name": "622", "route_color": "#F98700", "arrival_time": "13:36:24", "departure_time": "13:36:24", "stop_sequence": 23, "headsign": "Terminal Capão Raso"}, {"trip_id": "6873480", "route_short_name": "658", "route_color": "#F98700", "arrival_time": "13:52:33", "departure_time": "13:52:33", "stop_sequence": 44, "headsign": "Terminal Capão Raso"}, {"trip_id": "6873440", "route_short_name": "658", "route_color": "#F98700", "arrival_time": "14:09:39", "departure_time": "14:09:39", "stop_sequence": 44, "headsign": "Terminal Capão Raso"}, {"trip_id": "6878349", "route_short_name": "622", "route_color": "#F98700", "arrival_time": "14:24:28", "departure_time": "14:24:28", "stop_sequence": 23, "headsign": "Terminal Capão Raso"}, {"trip_id": "6873509", "route_short_name": "658", "route_color": "#F98700", "arrival_time": "14:30:37", "departure_time": "14:30:37", "stop_sequence": 44, "headsign": "Terminal Capão Raso"}, {"trip_id": "6873412", "route_short_name": "658", "route_color": "#F98700", "arrival_time": "14:52:35", "departure_time": "14:52:35", "stop_sequence": 44, "headsign": "Terminal Capão Raso"}, {"trip_id": "6878351", "route_short_name": "622", "route_color": "#F98700", "arrival_time": "15:12:28", "departure_time": "15:12:28", "stop_sequence": 23, "headsign": "Terminal Capão Raso"}, {"trip_id": "6873482", "route_short_name": "658", "route_color": "#F98700", "arrival_time": "15:14:33", "departure_time": "15:14:33", "stop_sequence": 44, "headsign": "Terminal Capão Raso"}, {"trip_id": "6873442", "route_short_name": "658", "route_color": "#F98700", "arrival_time": "15:36:31", "departure_time": "15:36:31", "stop_sequence": 44, "headsign": "Terminal Capão Raso"}], "sunday": [{"trip_id": "6873468", "route_short_name": "658", "route_color": "#F98700", "arrival_time": "05:36:43", "departure_time": "05:36:43", "stop_sequence": 44, "headsign": "Terminal Capão Raso"}, {"trip_id": "6878327", "route_short_name": "622", "route_color": "#F98700", "arrival_time": "05:41:32", "departure_time": "05:41:32", "stop_sequence": 23, "headsign": "Terminal Capão Raso"}, {"trip_id": "6873386", "route_short_name": "658", "route_color": "#F98700", "arrival_time": "05:47:41", "departure_time": "05:47:41", "stop_sequence": 44, "headsign": "Terminal Capão Raso"}, {"trip_id": "6873428", "route_short_name": "658", "route_color": "#F98700", "arrival_time": "05:58:41", "departure_time": "05:58:41", "stop_sequence": 44, "headsign": "Terminal Capão Raso"}, {"trip_id": "6873463", "route_short_name": "658", "route_color": "#F98700", "arrival_time": "06:09:41", "departure_time": "06:09:41", "stop_sequence": 44, "headsign": "Terminal Capão Raso"}, {"trip_id": "6873497", "route_short_name": "658", "route_color": "#F98700", "arrival_time": "06:20:41", "departure_time": "06:20:41", "stop_sequence": 44, "headsign": "Terminal Capão Raso"}, {"trip_id": "6878329", "route_short_name": "622", "route_color": "#F98700", "arrival_time": "06:26:32", "departure_time": "06:26:32", "stop_sequence": 23, "headsign": "Terminal Capão Raso"}, {"trip_id": "6873400", "route_short_name": "658", "route_color": "#F98700", "arrival_time": "06:31:41", "departure_time": "06:31:41", "stop_sequence": 44, "headsign": "Terminal Capão Raso"}, {"trip_id": "6873456", "route_short_name": "658", "route_color": "#F98700", "arrival_time": "06:43:39", "departure_time": "06:43:39", "stop_sequence": 44, "headsign": "Terminal Capão Raso"}, {"trip_id": "6873470", "route_short_name": "658", "route_color": "#F98700", "arrival_time": "06:55:37", "departure_time": "06:55:37", "stop_sequence": 44, "headsign": "Terminal Capão Raso"}, {"trip_id": "6873388", "route_short_name": "658", "route_color": "#F98700", "arrival_time": "07:07:35", "departure_time": "07:07:35", "stop_sequence": 44, "headsign": "Terminal Capão Raso"}, {"trip_id": "6878331", "route_short_name": "622", "route_color": "#F98700", "arrival_time": "07:12:28", "departure_time": "07:12:28", "stop_sequence": 23, "headsign": "Terminal Capão Raso"}, {"trip_id": "6873430", "route_short_name": "658", "route_color": "#F98700", "arrival_time": "07:19:33", "departure_time": "07:19:33", "stop_sequence": 44, "headsign": "Terminal Capão Raso"}, {"trip_id": "6873465", "route_short_name": "658", "route_color": "#F98700", "arrival_time": "07:32:29", "departure_time": "07:32:29", "stop_sequence": 44, "headsign": "Terminal Capão Raso"}, {"trip_id": "6873499", "route_short_name": "658", "route_color": "#F98700", "arrival_time": "07:45:25", "departure_time": "07:45:25", "stop_sequence": 44, "headsign": "Terminal Capão Raso"}, {"trip_id": "6878333", "route_short_name": "622", "route_color": "#F98700", "arrival_time": "08:00:28", "departure_time": "08:00:28", "stop_sequence": 23, "headsign": "Terminal Capão Raso"}, {"trip_id": "6873402", "route_short_name": "658", "route_color": "#F98700", "arrival_time": "08:01:17", "departure_time": "08:01:17", "stop_sequence": 44, "headsign": "Terminal Capão Raso"}, {"trip_id": "6873472", "route_short_name": "658", "route_color": "#F98700", "arrival_time": "08:22:23", "departure_time": "08:22:23", "stop_sequence": 44, "headsign": "Terminal Capão Raso"}, {"trip_id": "6873432", "route_short_name": "658", "route_color": "#F98700", "arrival_time": "08:42:31", "departure_time": "08:42:31", "stop_sequence": 44, "headsign": "Terminal Capão Raso"}, {"trip_id": "6878335", "route_short_name": "622", "route_color": "#F98700", "arrival_time": "08:49:24", "departure_time": "08:49:24", "stop_sequence": 23, "headsign": "Terminal Capão Raso"}, {"trip_id": "6873501", "route_short_name": "658", "route_color": "#F98700", "arrival_time": "09:02:43", "departure_time": "09:02:43", "stop_sequence": 44, "headsign": "Terminal Capão Raso"}, {"trip_id": "6873404", "route_short_name": "658", "route_color": "#F98700", "arrival_time": "09:22:41", "departure_time": "09:22:41", "stop_sequence": 44, "headsign": "Terminal Capão Raso"}, {"trip_id": "6878337", "route_short_name": "622", "route_color": "#F98700", "arrival_time": "09:36:28", "departure_time": "09:36:28", "stop_sequence": 23, "headsign": "Terminal Capão Raso"}, {"trip_id": "6873474", "route_short_name": "658", "route_color": "#F98700", "arrival_time": "09:42:39", "departure_time": "09:42:39", "stop_sequence": 44, "headsign": "Terminal Capão Raso"}, {"trip_id": "6873434", "route_short_name": "658", "route_color": "#F98700", "arrival_time": "10:02:39", "departure_time": "10:02:39", "stop_sequence": 44, "headsign": "Terminal Capão Raso"}, {"trip_id": "6873503", "route_short_name": "658", "route_color": "#F98700", "arrival_time": "10:22:39", "departure_time": "10:22:39", "stop_sequence": 44, "headsign": "Terminal Capão Raso"}, {"trip_id": "6878339", "route_short_name": "622", "route_color": "#F98700", "arrival_time": "10:24:24", "departure_time": "10:24:24", "stop_sequence": 23, "headsign": "Terminal Capão Raso"}, {"trip_id": "6873406", "route_short_name": "658", "route_color": "#F98700", "arrival_time": "10:42:39", "departure_time": "10:42:39", "stop_sequence": 44, "headsign": "Terminal Capão Raso"}, {"trip_id": "6873476", "route_short_name": "658", "route_color": "#F98700", "arrival_time": "11:02:39", "departure_time": "11:02:39", "stop_sequence": 44, "headsign": "Terminal Capão Raso"}, {"trip_id": "6878341", "route_short_name": "622", "route_color": "#F98700", "arrival_time": "11:11:28", "departure_time": "11:11:28", "stop_sequence": 23, "headsign": "Terminal Capão Raso"}, {"trip_id": "6873436", "route_short_name": "658", "route_color": "#F98700", "arrival_time": "11:22:39", "departure_time": "11:22:39", "stop_sequence": 44, "headsign": "Terminal Capão Raso"}, {"trip_id": "6873505", "route_short_name": "658", "route_color": "#F98700", "arrival_time": "11:39:45", "departure_time": "11:39:45", "stop_sequence": 44, "headsign": "Terminal Capão Raso"}, {"trip_id": "6873391", "route_short_name": "658", "route_color": "#F98700", "arrival_time": "11:56:39", "departure_time": "11:56:39", "stop_sequence": 44, "headsign": "Terminal Capão Raso"}, {"trip_id": "6878343", "route_short_name": "622", "route_color": "#F98700", "arrival_time": "11:58:28", "departure_time": "11:58:28", "stop_sequence": 23, "headsign": "Terminal Capão Raso"}, {"trip_id": "6873408", "route_short_name": "658", "route_color": "#F98700", "arrival_time": "12:13:33", "departure_time": "12:13:33", "stop_sequence": 44, "headsign": "Terminal Capão Raso"}, {"trip_id": "6873478", "route_short_name": "658", "route_color": "#F98700", "arrival_time": "12:30:31", "departure_time": "12:30:31", "stop_sequence": 44, "headsign": "Terminal Capão Raso"}, {"trip_id": "6873438", "route_short_name": "658", "route_color": "#F98700", "arrival_time": "12:46:31", "departure_time": "12:46:31", "stop_sequence": 44, "headsign": "Terminal Capão Raso"}, {"trip_id": "6878345", "route_short_name": "622", "route_color": "#F98700", "arrival_time": "12:47:24", "departure_time": "12:47:24", "stop_sequence": 23, "headsign": "Terminal Capão Raso"}, {"trip_id": "6873507", "route_short_name": "658", "route_color": "#F98700", "arrival_time": "13:03:29", "departure_time": "13:03:29", "stop_sequence": 44, "headsign": "Terminal Capão Raso"}, {"trip_id": "6873393", "route_short_name": "658", "route_color": "#F98700", "arrival_time": "13:19:31", "departure_time": "13:19:31", "stop_sequence": 44, "headsign": "Terminal Capão Raso"}, {"trip_id": "6873410", "route_short_name": "658", "route_color": "#F98700", "arrival_time": "13:35:33", "departure_time": "13:35:33", "stop_sequence": 44, "headsign": "Terminal Capão Raso"}, {"trip_id": "6878347", "route_short_name": "622", "route_color": "#F98700", "arrival_time": "13:36:24", "departure_time": "13:36:24", "stop_sequence": 23, "headsign": "Terminal Capão Raso"}, {"trip_id": "6873480", "route_short_name": "658", "route_color": "#F98700", "arrival_time": "13:52:33", "departure_time": "13:52:33", "stop_sequence": 44, "headsign": "Terminal Capão Raso"}, {"trip_id": "6873440", "route_short_name": "658", "route_color": "#F98700", "arrival_time": "14:09:39", "departure_time": "14:09:39", "stop_sequence": 44, "headsign": "Terminal Capão Raso"}, {"trip_id": "6878349", "route_short_name": "622", "route_color": "#F98700", "arrival_time": "14:24:28", "departure_time": "14:24:28", "stop_sequence": 23, "headsign": "Terminal Capão Raso"}, {"trip_id": "6873509", "route_short_name": "658", "route_color": "#F98700", "arrival_time": "14:30:37", "departure_time": "14:30:37", "stop_sequence": 44, "headsign": "Terminal Capão Raso"}, {"trip_id": "6873412", "route_short_name": "658", "route_color": "#F98700", "arrival_time": "14:52:35", "departure_time": "14:52:35", "stop_sequence": 44, "headsign": "Terminal Capão Raso"}, {"trip_id": "6878351", "route_short_name": "622", "route_color": "#F98700", "arrival_time": "15:12:28", "departure_time": "15:12:28", "stop_sequence": 23, "headsign": "Terminal Capão Raso"}, {"trip_id": "6873482", "route_short_name": "658", "route_color": "#F98700", "arrival_time": "15:14:33", "departure_time": "15:14:33", "stop_sequence": 44, "headsign": "Terminal Capão Raso"}, {"trip_id": "6873442", "route_short_name": "658", "route_color": "#F98700", "arrival_time": "15:36:31", "departure_time": "15:36:31", "stop_sequence": 44, "headsign": "Terminal Capão Raso"}]}