{"times": [{"trip_id": "6883611", "route_short_name": "304", "route_color": "#FF0000", "arrival_time": "06:15:18", "departure_time": "06:15:18", "stop_sequence": 8, "headsign": "Terminal Campo Comprido"}, {"trip_id": "6883617", "route_short_name": "304", "route_color": "#FF0000", "arrival_time": "06:21:26", "departure_time": "06:21:26", "stop_sequence": 8, "headsign": "Terminal Campo Comprido"}, {"trip_id": "6883630", "route_short_name": "304", "route_color": "#FF0000", "arrival_time": "06:27:34", "departure_time": "06:27:34", "stop_sequence": 8, "headsign": "Terminal Campo Comprido"}, {"trip_id": "6883635", "route_short_name": "304", "route_color": "#FF0000", "arrival_time": "06:32:41", "departure_time": "06:32:41", "stop_sequence": 8, "headsign": "Terminal Campo Comprido"}, {"trip_id": "6883667", "route_short_name": "304", "route_color": "#FF0000", "arrival_time": "06:38:41", "departure_time": "06:38:41", "stop_sequence": 8, "headsign": "Terminal Campo Comprido"}, {"trip_id": "6883675", "route_short_name": "304", "route_color": "#FF0000", "arrival_time": "06:43:41", "departure_time": "06:43:41", "stop_sequence": 8, "headsign": "Terminal Campo Comprido"}, {"trip_id": "6883700", "route_short_name": "304", "route_color": "#FF0000", "arrival_time": "06:49:34", "departure_time": "06:49:34", "stop_sequence": 8, "headsign": "Terminal Campo Comprido"}, {"trip_id": "6883712", "route_short_name": "304", "route_color": "#FF0000", "arrival_time": "06:54:34", "departure_time": "06:54:34", "stop_sequence": 8, "headsign": "Terminal Campo Comprido"}, {"trip_id": "6883730", "route_short_name": "304", "route_color": "#FF0000", "arrival_time": "06:59:34", "departure_time": "06:59:34", "stop_sequence": 8, "headsign": "Terminal Campo Comprido"}, {"trip_id": "6883746", "route_short_name": "304", "route_color": "#FF0000", "arrival_time": "07:05:34", "departure_time": "07:05:34", "stop_sequence": 8, "headsign": "Terminal Campo Comprido"}, {"trip_id": "6883749", "route_short_name": "304", "route_color": "#FF0000", "arrival_time": "07:11:34", "departure_time": "07:11:34", "stop_sequence": 8, "headsign": "Terminal Campo Comprido"}, {"trip_id": "6883762", "route_short_name": "304", "route_color": "#FF0000", "arrival_time": "07:16:34", "departure_time": "07:16:34", "stop_sequence": 8, "headsign": "Terminal Campo Comprido"}, {"trip_id": "6883768", "route_short_name": "304", "route_color": "#FF0000", "arrival_time": "07:22:34", "departure_time": "07:22:34", "stop_sequence": 8, "headsign": "Terminal Campo Comprido"}, {"trip_id": "6883655", "route_short_name": "304", "route_color": "#FF0000", "arrival_time": "07:28:37", "departure_time": "07:28:37", "stop_sequence": 8, "headsign": "Terminal Campo Comprido"}, {"trip_id": "6883695", "route_short_name": "304", "route_color": "#FF0000", "arrival_time": "07:34:37", "departure_time": "07:34:37", "stop_sequence": 8, "headsign": "Terminal Campo Comprido"}, {"trip_id": "6883771", "route_short_name": "304", "route_color": "#FF0000", "arrival_time": "07:41:26", "departure_time": "07:41:26", "stop_sequence": 8, "headsign": "Terminal Campo Comprido"}, {"trip_id": "6883709", "route_short_name": "304", "route_color": "#FF0000", "arrival_time": "07:47:30", "departure_time": "07:47:30", "stop_sequence": 8, "headsign": "Terminal Campo Comprido"}, {"trip_id": "6883726", "route_short_name": "304", "route_color": "#FF0000", "arrival_time": "07:53:30", "departure_time": "07:53:30", "stop_sequence": 8, "headsign": "Terminal Campo Comprido"}, {"trip_id": "6883734", "route_short_name": "304", "route_color": "#FF0000", "arrival_time": "07:59:30", "departure_time": "07:59:30", "stop_sequence": 8, "headsign": "Terminal Campo Comprido"}, {"trip_id": "6883613", "route_short_name": "304", "route_color": "#FF0000", "arrival_time": "08:06:18", "departure_time": "08:06:18", "stop_sequence": 8, "headsign": "Terminal Campo Comprido"}, {"trip_id": "6883619", "route_short_name": "304", "route_color": "#FF0000", "arrival_time": "08:13:26", "departure_time": "08:13:26", "stop_sequence": 8, "headsign": "Terminal Campo Comprido"}, {"trip_id": "6883632", "route_short_name": "304", "route_color": "#FF0000", "arrival_time": "08:20:18", "departure_time": "08:20:18", "stop_sequence": 8, "headsign": "Terminal Campo Comprido"}, {"trip_id": "6883637", "route_short_name": "304", "route_color": "#FF0000", "arrival_time": "08:27:18", "departure_time": "08:27:18", "stop_sequence": 8, "headsign": "Terminal Campo Comprido"}, {"trip_id": "6883669", "route_short_name": "304", "route_color": "#FF0000", "arrival_time": "08:34:18", "departure_time": "08:34:18", "stop_sequence": 8, "headsign": "Terminal Campo Comprido"}, {"trip_id": "6883677", "route_short_name": "304", "route_color": "#FF0000", "arrival_time": "08:41:11", "departure_time": "08:41:11", "stop_sequence": 8, "headsign": "Terminal Campo Comprido"}, {"trip_id": "6883702", "route_short_name": "304", "route_color": "#FF0000", "arrival_time": "08:48:03", "departure_time": "08:48:03", "stop_sequence": 8, "headsign": "Terminal Campo Comprido"}, {"trip_id": "6883714", "route_short_name": "304", "route_color": "#FF0000", "arrival_time": "08:54:55", "departure_time": "08:54:55", "stop_sequence": 8, "headsign": "Terminal Campo Comprido"}, {"trip_id": "6883732", "route_short_name": "304", "route_color": "#FF0000", "arrival_time": "09:00:55", "departure_time": "09:00:55", "stop_sequence": 8, "headsign": "Terminal Campo Comprido"}, {"trip_id": "6883751", "route_short_name": "304", "route_color": "#FF0000", "arrival_time": "09:12:03", "departure_time": "09:12:03", "stop_sequence": 8, "headsign": "Terminal Campo Comprido"}, {"trip_id": "6883657", "route_short_name": "304", "route_color": "#FF0000", "arrival_time": "09:25:19", "departure_time": "09:25:19", "stop_sequence": 8, "headsign": "Terminal Campo Comprido"}, {"trip_id": "6883773", "route_short_name": "304", "route_color": "#FF0000", "arrival_time": "09:40:03", "departure_time": "09:40:03", "stop_sequence": 8, "headsign": "Terminal Campo Comprido"}, {"trip_id": "6883736", "route_short_name": "304", "route_color": "#FF0000", "arrival_time": "09:54:26", "departure_time": "09:54:26", "stop_sequence": 8, "headsign": "Terminal Campo Comprido"}, {"trip_id": "6883621", "route_short_name": "304", "route_color": "#FF0000", "arrival_time": "10:08:18", "departure_time": "10:08:18", "stop_sequence": 8, "headsign": "Terminal Campo Comprido"}, {"trip_id": "6883639", "route_short_name": "304", "route_color": "#FF0000", "arrival_time": "10:22:18", "departure_time": "10:22:18", "stop_sequence": 8, "headsign": "Terminal Campo Comprido"}, {"trip_id": "6883679", "route_short_name": "304", "route_color": "#FF0000", "arrival_time": "10:37:18", "departure_time": "10:37:18", "stop_sequence": 8, "headsign": "Terminal Campo Comprido"}, {"trip_id": "6883716", "route_short_name": "304", "route_color": "#FF0000", "arrival_time": "10:52:18", "departure_time": "10:52:18", "stop_sequence": 8, "headsign": "Terminal Campo Comprido"}, {"trip_id": "6883753", "route_short_name": "304", "route_color": "#FF0000", "arrival_time": "11:07:18", "departure_time": "11:07:18", "stop_sequence": 8, "headsign": "Terminal Campo Comprido"}, {"trip_id": "6883659", "route_short_name": "304", "route_color": "#FF0000", "arrival_time": "11:20:26", "departure_time": "11:20:26", "stop_sequence": 8, "headsign": "Terminal Campo Comprido"}, {"trip_id": "6883775", "route_short_name": "304", "route_color": "#FF0000", "arrival_time": "11:35:18", "departure_time": "11:35:18", "stop_sequence": 8, "headsign": "Terminal Campo Comprido"}, {"trip_id": "6883738", "route_short_name": "304", "route_color": "#FF0000", "arrival_time": "11:49:26", "departure_time": "11:49:26", "stop_sequence": 8, "headsign": "Terminal Campo Comprido"}, {"trip_id": "6883623", "route_short_name": "304", "route_color": "#FF0000", "arrival_time": "12:04:18", "departure_time": "12:04:18", "stop_sequence": 8, "headsign": "Terminal Campo Comprido"}, {"trip_id": "6883641", "route_short_name": "304", "route_color": "#FF0000", "arrival_time": "12:18:18", "departure_time": "12:18:18", "stop_sequence": 8, "headsign": "Terminal Campo Comprido"}, {"trip_id": "6883681", "route_short_name": "304", "route_color": "#FF0000", "arrival_time": "12:33:18", "departure_time": "12:33:18", "stop_sequence": 8, "headsign": "Terminal Campo Comprido"}, {"trip_id": "6883718", "route_short_name": "304", "route_color": "#FF0000", "arrival_time": "12:48:18", "departure_time": "12:48:18", "stop_sequence": 8, "headsign": "Terminal Campo Comprido"}, {"trip_id": "6883755", "route_short_name": "304", "route_color": "#FF0000", "arrival_time": "13:03:18", "departure_time": "13:03:18", "stop_sequence": 8, "headsign": "Terminal Campo Comprido"}, {"trip_id": "6883661", "route_short_name": "304", "route_color": "#FF0000", "arrival_time": "13:16:26", "departure_time": "13:16:26", "stop_sequence": 8, "headsign": "Terminal Campo Comprido"}, {"trip_id": "6883777", "route_short_name": "304", "route_color": "#FF0000", "arrival_time": "13:31:18", "departure_time": "13:31:18", "stop_sequence": 8, "headsign": "Terminal Campo Comprido"}, {"trip_id": "6883740", "route_short_name": "304", "route_color": "#FF0000", "arrival_time": "13:45:26", "departure_time": "13:45:26", "stop_sequence": 8, "headsign": "Terminal Campo Comprido"}, {"trip_id": "6883625", "route_short_name": "304", "route_color": "#FF0000", "arrival_time": "14:00:18", "departure_time": "14:00:18", "stop_sequence": 8, "headsign": "Terminal Campo Comprido"}, {"trip_id": "6883643", "route_short_name": "304", "route_color": "#FF0000", "arrival_time": "14:14:18", "departure_time": "14:14:18", "stop_sequence": 8, "headsign": "Terminal Campo Comprido"}], "day": "thursday"}